argos_spacy_compatibility/__init__.py
argos_spacy_compatibility/apis.py
argos_spacy_compatibility/apply_bpe.py
argos_spacy_compatibility/argospm.py
argos_spacy_compatibility/cli.py
argos_spacy_compatibility/fewshot.py
argos_spacy_compatibility/img/icon.icns
argos_spacy_compatibility/img/icon.png
argos_spacy_compatibility/languages.csv
argos_spacy_compatibility/models.py
argos_spacy_compatibility/networking.py
argos_spacy_compatibility/package.py
argos_spacy_compatibility/sbd.py
argos_spacy_compatibility/settings.py
argos_spacy_compatibility/tags.py
argos_spacy_compatibility/tokenizer.py
argos_spacy_compatibility/translate.py
argos_spacy_compatibility/utils.py
argos_spacy_compatibility-0.1.0.dist-info/LICENSE
argos_spacy_compatibility-0.1.0.dist-info/METADATA
argos_spacy_compatibility-0.1.0.dist-info/WHEEL
argos_spacy_compatibility-0.1.0.dist-info/entry_points.txt
argos_spacy_compatibility-0.1.0.dist-info/RECORD
