Metadata-Version: 2.1
Name: argos-spacy-compatibility
Version: 0.1.0
Summary: Compatiblity fix for argostranslate. Should no longer be required post 1.9.7
License: MIT
Author: Your Name
Author-email: you@example.com
Requires-Python: >=3.10,<3.13
Classifier: License :: OSI Approved :: MIT License
Classifier: Programming Language :: Python :: 3
Classifier: Programming Language :: Python :: 3.10
Classifier: Programming Language :: Python :: 3.11
Classifier: Programming Language :: Python :: 3.12
Requires-Dist: ctranslate2 (>=4.0,<5.0)
Requires-Dist: packaging
Requires-Dist: sacremoses (==0.0.53)
Requires-Dist: sentencepiece (==0.2.0)
Requires-Dist: spacy
